PenguinServices/DateRanger.py
PenguinServices/FileSystem.py
PenguinServices/MiscUtils.py
PenguinServices/Networking.py
PenguinServices/OperatingSystem.py
PenguinServices/Security.py
PenguinServices/ShellAlternatives.py
PenguinServices/Terminal.py
PenguinServices/__init__.py
Penguin_Services-2.0.0.dist-info/LICENSE
Penguin_Services-2.0.0.dist-info/METADATA
Penguin_Services-2.0.0.dist-info/WHEEL
Penguin_Services-2.0.0.dist-info/top_level.txt
Penguin_Services-2.0.0.dist-info/RECORD
